{
    "title": "D.O.D feat. Carla Monroe - Still Sleepless (Ekko & Sidetrack Remix)",
    "id": "qFPBWJNxL3s",
    "filename": "D.O.D feat. Carla Monroe - Still Sleepless (Ekko & Sidetrack Remix) [qFPBWJNxL3s].ogg",
    "artist": "Axtone",
    "album": null,
    "bpm": 176,
    "initial_key": "C#",
    "camelot": "3B",
    "replaygain_track_gain": "1.12 dB",
    "replaygain_track_peak": "1.000000",
    "cover": "D.O.D feat. Carla Monroe - Still Sleepless (Ekko & Sidetrack Remix) [qFPBWJNxL3s].png"
}